__init__.py
celltraj_1apr21.py
cli.py
features.py
imageprep.py
model.py
spatial.py
trajectory.py
trajectory_legacy.py
translate.py
utilities.py
celltraj-0.1.76.dist-info/licenses/LICENSE
celltraj-0.1.76.dist-info/METADATA
celltraj-0.1.76.dist-info/WHEEL
celltraj-0.1.76.dist-info/top_level.txt
celltraj-0.1.76.dist-info/RECORD
